libnacl/__init__.py
libnacl/aead.py
libnacl/base.py
libnacl/blake.py
libnacl/dual.py
libnacl/encode.py
libnacl/public.py
libnacl/sealed.py
libnacl/secret.py
libnacl/secret_easy.py
libnacl/sign.py
libnacl/utils.py
libnacl-2.0.0.dist-info/LICENSE
libnacl-2.0.0.dist-info/METADATA
libnacl-2.0.0.dist-info/WHEEL
libnacl-2.0.0.dist-info/RECORD
