Metadata-Version: 2.1
Name: libnacl
Version: 2.0.0
Summary: Python bindings for libsodium based on ctypes
Home-page: https://libnacl.readthedocs.org
License: Apache-2.0
Author: Thomas S Hatch
Author-email: thatch45@gmail.com
Requires-Python: >=3.4,<4.0
Classifier: Development Status :: 5 - Production/Stable
Classifier: Intended Audience :: Developers
Classifier: License :: OSI Approved :: Apache Software License
Classifier: Operating System :: OS Independent
Classifier: Programming Language :: Python
Classifier: Programming Language :: Python :: 3
Classifier: Programming Language :: Python :: 3.4
Classifier: Programming Language :: Python :: 3.5
Classifier: Programming Language :: Python :: 3.6
Classifier: Programming Language :: Python :: 3.7
Classifier: Programming Language :: Python :: 3.8
Classifier: Programming Language :: Python :: 3.9
Classifier: Programming Language :: Python :: 3.10
Classifier: Programming Language :: Python :: 3.11
Classifier: Programming Language :: Python :: 2.6
Classifier: Programming Language :: Python :: 2.7
Classifier: Topic :: Security :: Cryptography
Project-URL: Documentation, https://libnacl.readthedocs.org
Project-URL: Repository, https://github.com/saltstack/libnacl
